{
  "query": {
    "bool": {
      "must": [
        {
          "multi_match": {
            "fields": [
              "description",
              "tariff_rate_quota_note",
              "rule_text",
              "tariff_line"
            ],
            "operator": "and",
            "query": "horses"
          }
        }
      ]
    }
  },
  "filter": {
    "bool": {
      "must": [
        {
          "terms": {
            "source": [
              "AUSTRALIA"
            ]
          }
        },
        {
          "terms": {
            "countries": [
              "US",
              "AU"
            ]
          }
        }
      ]
    }
  }
}
