{
  "Arsenic Remediation in Drinking Water": {
    "Safe Drinking Water Act - Arsenic Rule": [
      "Adsorption Processes",
      "Ion Exchange Processes",
      "Membrane Processes",
      "Point-of-Use (POU) Devices",
      "Precipitative Processes",
      "Related Technologies for Safe Water Drinking Act - Arsenic Rule: Arsenic Remediation",
      "Residual Management Processes"
    ]
  },
  "Biosolid/Sludge Management, Use, or Disposal": {
    "Standards for the Use or Disposal of Sewage Sludge": [
      "Conditioning Technology or Processes",
      "Dewatering Technology or Processes",
      "Drying Technology or Processes",
      "Re-use or Disposal Processes",
      "Related Technologies for Standards for Use or Disposal of Sewage Sludge: Biosolid/Sludge Management",
      "Stabilization Technology or Processes",
      "Thermal Conversion Technology or Processes",
      "Thickening Technology or Processes"
    ]
  },
  "Drinking Water Treatment for Surface Water Sources": {
    "Safe Drinking Water Act - Surface Water Treatment Rule": [
      "Cartridge Filters",
      "Chemical Disinfection",
      "Diatomaceous Earth Filtration",
      "Package Plants",
      "Physical and Chemical Treatment Processes",
      "Process Monitoring Technologies",
      "Related Technologies for Surface Water Treatment Rule",
      "Slow Sand Filtration"
    ]
  },
  "Emissions Control for Oil and Natural Gas Processing": {
    "Standards of Performance for New Stationary Sources: Oil and Gas": [
      "Absorption Towers",
      "Flash Tanks",
      "Glycol Dehydrators",
      "Related Technologies for NSPS: Oil and Gas Processing Emissions Control"
    ]
  },
  "Emissions Control from Large Marine Diesel Engines": {
    "Control of Emissions from New and In-Use Marine Engines and Vessels": [
      "Fuel Switching - Low Sulphur Diesel",
      "Fuel Switching - Natural Gas",
      "Fuel Switching - SOx Scrubbers",
      "NOx - Exhaust Gas Recirculation",
      "NOx - Natural Gas Engine",
      "NOx - Selective Catalytic Reduction",
      "NOx - Water Injection",
      "Related Technologies for Marine Diesel Engine Emissions Control: Large Marine Diesel Engines"
    ]
  },
  "Groundwater Remediation": {
    "Clean Water Act": [
      "Air Sparging",
      "Anaerobic/anoxic/oxic (A2O)",
      "Anoxic zone (following aeration)",
      "Anoxic/oxic (A/O)",
      "Biological aerated filtration",
      "Bioremediation",
      "Chemical Precipitation for Nitrogen and Phosphorus",
      "Chemical Precipitation for Phosphorus",
      "Chemical Treatment",
      "Denitrification Filters for Nitrogen",
      "Denitrification Filters for Nitrogen and Phosphorus",
      "Enhanced biological phosphorus removal (EBPR) with volatile fatty acids (VFA) addition and filters",
      "Filtration",
      "Flushing",
      "In-Well Air Stripping",
      "Integrated fixed-film activated sludge (IFAS)",
      "MLE/3-stage Westbank",
      "Membrane Filtration",
      "Membrane bioreactor (MBR)",
      "Moving bed biofilm reactor (MBBR)",
      "Multi-Phase Extraction",
      "Permeable Reactive Barrier",
      "Phytoremediation",
      "Pump and Treat",
      "Related Technologies for Clean Water Act: Groundwater Remediation",
      "Related Technologies for Clean Water Act: Municipal Nutrient Removal",
      "Sequencing batch reactor (SBR)/cyclic activated sludge",
      "Step-feed activated sludge (AS)",
      "Step-feed with selector",
      "Tertiary clarifier/tertiary filter"
    ],
    "Comprehensive Environmental Response, Compensation and Liability Act": [
      "Air Sparging",
      "Bioremediation",
      "Chemical Treatment",
      "Flushing",
      "In-Well Air Stripping",
      "Multi-Phase Extraction",
      "Permeable Reactive Barrier",
      "Phytoremediation",
      "Pump and Treat",
      "Related Technologies for CERCLA: Groundwater Remediation"
    ]
  },
  "Industrial Wastewater Pollution Control": {
    "Clean Water Act – Industrial Regulations": [
      "Activated Carbon",
      "Adsorptive Media",
      "Aeration and Air Stripping",
      "Biological Filtration",
      "Biological Treatment Processes",
      "Chemical Disinfection",
      "Chemical Treatment",
      "Diatomaceous Earth Filtration",
      "GAC Isotherm",
      "Ion Exchange",
      "Membrane Filtration",
      "Membrane Separation",
      "Ozone + Hydrogen Peroxide Disinfection",
      "Ozone Disinfection",
      "Permanganate",
      "Physical and Chemical Treatment Processes",
      "Precipitative Softening",
      "Pressure Filtration",
      "Related Technologies for CWA Industrial Regulations",
      "Slow Sand Filtration",
      "UV + Hydrogen Peroxide Disinfection",
      "UV + Ozone Disinfection",
      "UV Disinfection"
    ]
  },
  "Mercury Emissions Control from Power Plants": {
    "Mercury and Air Toxics Standards": [
      "Acid Gases - Dry Sorbent Injection",
      "Acid Gases - Dry Sorbent Injection with Electrostatic Precipitators",
      "Acid Gases - Dry Sorbent Injection with Fabric Filters",
      "Acid Gases - Flue-gas Desulfurization",
      "Dioxins & Furans - Work Practice Standard (inspection, adjustment, and/or maintenance and repairs to ensure optimal combustion)",
      "Mercury - Activated Carbon Injection",
      "Mercury - Activated Carbon Injection with Fabric Filter",
      "Mercury - Electrostatic Precipitators",
      "Mercury - Flue-gas Desulfurization",
      "Mercury - Selective Catalytic Reduction",
      "Non-Mercury Metals - Fabric Filter, Electrostatic Precipitators",
      "Related Technologies for Mercury and Air Toxics Standards: Mercury Emissions Control from Power Plants",
      "Sulphur Dioxide - Dry Sorbent Injection",
      "Sulphur Dioxide - Flue-gas Desulphurization"
    ]
  },
  "Municipal Landfill Standards": {
    "Standards of Performance for New Stationary Sources: Landfills and Municipal Waste": [
      "Bioreactors",
      "Controlled Injection Systems",
      "Landfill Control Systems",
      "Landfill Covers",
      "Landfill Gas Air Monitoring",
      "Landfill Gas Collection",
      "Landfill Groundwater Monitoring",
      "Leachate Collection Systems",
      "Liners",
      "Related Technologies for NSPS: Municipal Landfill Standards"
    ]
  },
  "Municipal Nutrient Removal": {
    "Clean Water Act": [
      "Air Sparging",
      "Anaerobic/anoxic/oxic (A2O)",
      "Anoxic zone (following aeration)",
      "Anoxic/oxic (A/O)",
      "Biological aerated filtration",
      "Bioremediation",
      "Chemical Precipitation for Nitrogen and Phosphorus",
      "Chemical Precipitation for Phosphorus",
      "Chemical Treatment",
      "Denitrification Filters for Nitrogen",
      "Denitrification Filters for Nitrogen and Phosphorus",
      "Enhanced biological phosphorus removal (EBPR) with volatile fatty acids (VFA) addition and filters",
      "Filtration",
      "Flushing",
      "In-Well Air Stripping",
      "Integrated fixed-film activated sludge (IFAS)",
      "MLE/3-stage Westbank",
      "Membrane Filtration",
      "Membrane bioreactor (MBR)",
      "Moving bed biofilm reactor (MBBR)",
      "Multi-Phase Extraction",
      "Permeable Reactive Barrier",
      "Phytoremediation",
      "Pump and Treat",
      "Related Technologies for Clean Water Act: Groundwater Remediation",
      "Related Technologies for Clean Water Act: Municipal Nutrient Removal",
      "Sequencing batch reactor (SBR)/cyclic activated sludge",
      "Step-feed activated sludge (AS)",
      "Step-feed with selector",
      "Tertiary clarifier/tertiary filter"
    ]
  },
  "NOx Emission Controls for Power Plants": {
    "Cross-State Air Pollution Rule (CSAPR)": [
      "Low NOx Burners",
      "Related Technologies for CSAPR: NOx Emissions Control from Power Plants",
      "Selective Catalytic Reduction",
      "Selective Non-Catalytic Reduction"
    ]
  },
  "Non-road Diesel Emissions Control": {
    "Non-road Exhaust Emissions Standards": [
      "Diesel Oxidation Catalysts",
      "Diesel Particulate Filters",
      "NOx - Selective Catalytic Reduction",
      "Related Technologies for Non-road Exhaust Emission Standards: Non-road Diesel Emissions Control"
    ]
  },
  "Secondary or Advanced Wastewater Treatment": {
    "Secondary Treatment Standards under the National Pollutant Discharge Elimination System (NPDES)": [
      "Biological Treatment Processes",
      "In-plant Wet Weather Management Processes",
      "Physical and Chemical Treatment Processes",
      "Process Monitoring Technologies",
      "Related Technologies for NPDES: Secondary or Advanced Wastewater Treatment Standards"
    ]
  },
  "Universal Waste": {
    "Standards for Universal Waste Management": [
      "CRT Recycling Technology",
      "E-Waste Recycling Technology",
      "Lamp Crushing Systems",
      "Mercury Recycling Technology",
      "Related Technologies for Standards for Universal Waste Management: Universal Waste"
    ]
  }
}
